opal_client/__init__.py
opal_client/cli.py
opal_client/client.py
opal_client/config.py
opal_client/limiter.py
opal_client/logger.py
opal_client/main.py
opal_client/utils.py
opal_client/callbacks/__init__.py
opal_client/callbacks/api.py
opal_client/callbacks/register.py
opal_client/callbacks/reporter.py
opal_client/data/__init__.py
opal_client/data/api.py
opal_client/data/fetcher.py
opal_client/data/rpc.py
opal_client/data/updater.py
opal_client/engine/__init__.py
opal_client/engine/logger.py
opal_client/engine/options.py
opal_client/engine/runner.py
opal_client/engine/healthcheck/opal.rego
opal_client/policy/__init__.py
opal_client/policy/api.py
opal_client/policy/fetcher.py
opal_client/policy/options.py
opal_client/policy/topics.py
opal_client/policy/updater.py
opal_client/policy_store/__init__.py
opal_client/policy_store/api.py
opal_client/policy_store/base_policy_store_client.py
opal_client/policy_store/cedar_client.py
opal_client/policy_store/mock_policy_store_client.py
opal_client/policy_store/opa_client.py
opal_client/policy_store/policy_store_client_factory.py
opal_client/policy_store/schemas.py
opal_client/tests/__init__.py
opal_client/tests/data_updater_test.py
opal_client/tests/engine_runner_test.py
opal_client/tests/opa_client_test.py
opal_client/tests/server_to_client_intergation_test.py
opal_client-0.9.0.dist-info/METADATA
opal_client-0.9.0.dist-info/WHEEL
opal_client-0.9.0.dist-info/entry_points.txt
opal_client-0.9.0.dist-info/top_level.txt
opal_client-0.9.0.dist-info/RECORD
