Metadata-Version: 2.1
Name: opal-client
Version: 0.9.0
Summary: OPAL is an administration layer for Open Policy Agent (OPA), detecting changes to both policy and data and pushing live updates to your agents. The opal-client is deployed alongside a policy-store (e.g: OPA), keeping it up-to-date, by connecting to an opal-server and subscribing to pub/sub updates for policy and policy data changes.
Home-page: https://github.com/permitio/opal
Author: Or Weis, Asaf Cohen
Author-email: or@permit.io
License: Apache 2.0
Classifier: Operating System :: OS Independent
Classifier: License :: OSI Approved :: Apache Software License
Classifier: Programming Language :: Python
Classifier: Programming Language :: Python :: 3
Classifier: Programming Language :: Python :: 3.9
Classifier: Programming Language :: Python :: 3.10
Classifier: Programming Language :: Python :: 3.11
Classifier: Programming Language :: Python :: 3.12
Classifier: Topic :: Internet :: WWW/HTTP :: HTTP Servers
Classifier: Topic :: Internet :: WWW/HTTP :: WSGI
Requires-Python: >=3.9
Requires-Dist: aiofiles<1,>=0.8.0
Requires-Dist: aiohttp<4,>=3.9.2
Requires-Dist: psutil>=5.9.1
Requires-Dist: tenacity<9,>=8.0.1
Requires-Dist: dpath<3,>=2.1.5
Requires-Dist: jsonpatch<2,>=1.33
Requires-Dist: opal-common==0.9.0
Requires-Dist: idna<4,>=3.3
Requires-Dist: typer<1,>=0.4.1
Requires-Dist: fastapi<1,>=0.109.1
Requires-Dist: fastapi-websocket-pubsub[all]<2,>=1.0.0
Requires-Dist: fastapi-websocket-rpc<1,>=0.1.28
Requires-Dist: websockets>=10.3
Requires-Dist: gunicorn>=23.0.0
Requires-Dist: pydantic[email]<2,>=1.9.1
Requires-Dist: starlette<1,>=0.40.0
Requires-Dist: uvicorn[standard]<1,>=0.17.6
Requires-Dist: fastapi-utils<1,>=0.2.1
Requires-Dist: setuptools>=70.0.0
Requires-Dist: anyio>=4.4.0
Requires-Dist: starlette>=0.40.0
Requires-Dist: typing-extensions; python_version < "3.8"
